clarabel-0.11.1.dist-info/METADATA
clarabel-0.11.1.dist-info/WHEEL
clarabel-0.11.1.dist-info/licenses/LICENSE.md
clarabel/__init__.py
clarabel/clarabel.pyd
clarabel-0.11.1.dist-info/RECORD
