Metadata-Version: 2.4
Name: clarabel
Version: 0.11.1
Classifier: Programming Language :: Rust
Requires-Dist: numpy
Requires-Dist: scipy
Requires-Dist: cffi
License-File: LICENSE.md
Summary: Clarabel Conic Interior Point Solver for Rust / Python
Keywords: convex,optimization,conic,solver,linear-programming
Author: Paul Goulart <paul.goulart@eng.ox.ac.uk>
Author-email: Paul Goulart <paul.goulart@eng.ox.ac.uk>
License: Apache-2.0
Requires-Python: >=3.9
Project-URL: Source Code, https://github.com/oxfordcontrol/Clarabel.rs
